pycanha_core/__init__.pyi
pycanha_core/gmm.pyi
pycanha_core/tmm.pyi
pycanha_core.cp313-win_amd64.pyd
pycanha_core-0.3.0.dist-info/METADATA
pycanha_core-0.3.0.dist-info/WHEEL
pycanha_core-0.3.0.dist-info/licenses/LICENSE
pycanha_core-0.3.0.dist-info/RECORD
